shortloop_python/__init__.py
shortloop_python/core/__init__.py
shortloop_python/core/always_capture_sync.py
shortloop_python/core/api_processor.py
shortloop_python/core/auto_configuration.py
shortloop_python/core/buffer/abstract_buffer_manager.py
shortloop_python/core/buffer/api_buffer_key.py
shortloop_python/core/buffer/buffer.py
shortloop_python/core/buffer/buffer_manager_worker.py
shortloop_python/core/buffer/discovered_buffer_manager.py
shortloop_python/core/buffer/no_op_buffer_manager.py
shortloop_python/core/buffer/registered_buffer_manager.py
shortloop_python/core/buffer/simple_buffer.py
shortloop_python/core/config/config_manager.py
shortloop_python/core/config/config_update_listener.py
shortloop_python/core/config/config_validators.py
shortloop_python/core/config/simple_config_manager.py
shortloop_python/core/constant/__init__.py
shortloop_python/core/constant/http_method.py
shortloop_python/core/constant/segment_template_type.py
shortloop_python/core/filter/__init__.py
shortloop_python/core/filter/always_capture_filter.py
shortloop_python/core/filter/filter.py
shortloop_python/core/http/__init__.py
shortloop_python/core/http/context.py
shortloop_python/core/http/http_connection.py
shortloop_python/core/http/http_request.py
shortloop_python/core/http/http_response.py
shortloop_python/core/model/__init__.py
shortloop_python/core/model/agent_config.py
shortloop_python/core/model/api_config.py
shortloop_python/core/model/api_sample.py
shortloop_python/core/model/black_list_rule.py
shortloop_python/core/model/observed_api.py
shortloop_python/core/model/sdk_options.py
shortloop_python/core/model/uri.py
shortloop_python/core/scheduled_timer.py
shortloop_python/core/shortlook_sdk.py
shortloop_python/core/util/filter_utils.py
shortloop_python/core/util/masking_utils.py
shortloop_python/core/util/uri_utils.py
shortloop_python/integrations/__init__.py
shortloop_python/integrations/django.py
shortloop_python/sdk_logger.py
shortloop_python/sdk_version.py
shortloop_python-0.1.8.dist-info/METADATA
shortloop_python-0.1.8.dist-info/WHEEL
shortloop_python-0.1.8.dist-info/RECORD
