Metadata-Version: 2.1
Name: shortloop-python
Version: 0.1.8
Summary: Official Shortloop SDK for Python
Home-page: https://shortloop.dev
Keywords: shortloop,middleware
Author: ShortLoop
Author-email: hello@shortloop.dev
Maintainer: ShortLoop
Maintainer-email: hello@shortloop.dev
Requires-Python: >=3.7
Classifier: Development Status :: 5 - Production/Stable
Classifier: Framework :: Django :: 3.2
Classifier: Framework :: Django :: 4
Classifier: Operating System :: OS Independent
Classifier: Programming Language :: Python :: 3
Classifier: Programming Language :: Python :: 3.7
Classifier: Programming Language :: Python :: 3.8
Classifier: Programming Language :: Python :: 3.9
Classifier: Programming Language :: Python :: 3.10
Classifier: Programming Language :: Python :: 3.11
Classifier: Topic :: Internet :: WWW/HTTP :: WSGI :: Middleware
Classifier: Topic :: Software Development
Project-URL: Documentation, https://docs.shortloop.dev
